news_2_pdf/__init__.py
news_2_pdf/article.py
news_2_pdf/find_links.py
news_2_pdf/index.py
news_2_pdf-0.0.40.dist-info/LICENSE
news_2_pdf-0.0.40.dist-info/METADATA
news_2_pdf-0.0.40.dist-info/WHEEL
news_2_pdf-0.0.40.dist-info/top_level.txt
news_2_pdf-0.0.40.dist-info/RECORD
